{"goodsList":[{"deliverytype2":"0","price":"15900","ca_code":"15020801","goodsnm":"4KG_햇찰보리쌀","pl_no":"395749617","deliveryinfo2":"0","shopImageUrl":"http://image.homeplus.co.kr/UserFiles/Pressimages/28/300/007972628_0.jpg","ca_code4":"","modelno":"8557123","ca_codeName":"","deliveryinfo":"유무료","url":"http://www.homeplus.co.kr/app.exhibition.main.PartnerMall.ghs?extends_id=enuri&service_cd=56010&nextUrl=/app.product.GoodDetail.ghs%3Fcomm%3Dusr.detail%26good_id%3D007972628%26extends_id%3Denuri%26service_cd%3D56010","imgurl":"http://image.homeplus.co.kr/UserFiles/Pressimages/28/204/007972628_0.jpg"},{"deliverytype2":"0","price":"3590","ca_code":"15030712","goodsnm":"신선특란_30입_홈플러스친환경","pl_no":"395683853","deliveryinfo2":"0","shopImageUrl":"http://image.homeplus.co.kr/UserFiles/Pressimages/91/300/009303391_0.jpg","ca_code4":"","modelno":"7610219","ca_codeName":"","deliveryinfo":"유무료","url":"http://www.homeplus.co.kr/app.exhibition.main.PartnerMall.ghs?extends_id=enuri&service_cd=56010&nextUrl=/app.product.GoodDetail.ghs%3Fcomm%3Dusr.detail%26good_id%3D009303391%26extends_id%3Denuri%26service_cd%3D56010","imgurl":"http://image.homeplus.co.kr/UserFiles/Pressimages/91/204/009303391_0.jpg"},{"deliverytype2":"1","price":"8990","ca_code":"1502","goodsnm":"2KG(봉)_성주꿀참외","pl_no":"2372858715","deliveryinfo2":"3000","shopImageUrl":"http://image.homeplus.co.kr/UserFiles/Pressimages/66/300/126168266_0.jpg","ca_code4":"","modelno":"0","ca_codeName":"","deliveryinfo":"3000","url":"http://www.homeplus.co.kr/app.exhibition.main.PartnerMall.ghs?extends_id=enuri&service_cd=56010&nextUrl=/app.product.GoodDetail.ghs%3Fcomm%3Dusr.detail%26good_id%3D126168266%26extends_id%3Denuri%26service_cd%3D56010","imgurl":"http://image.homeplus.co.kr/UserFiles/Pressimages/66/204/126168266_0.jpg"},{"deliverytype2":"1","price":"8490","ca_code":"15030713","goodsnm":"800G*2입_닭볶음탕용(기획팩)","pl_no":"2220076329","deliveryinfo2":"3000","shopImageUrl":"http://image.homeplus.co.kr/UserFiles/Pressimages/25/300/125728625_0.jpg","ca_code4":"","modelno":"12886489","ca_codeName":"","deliveryinfo":"3000","url":"http://www.homeplus.co.kr/app.exhibition.main.PartnerMall.ghs?extends_id=enuri&service_cd=56010&nextUrl=/app.product.GoodDetail.ghs%3Fcomm%3Dusr.detail%26good_id%3D125728625%26extends_id%3Denuri%26service_cd%3D56010","imgurl":"http://image.homeplus.co.kr/UserFiles/Pressimages/25/204/125728625_0.jpg"},{"deliverytype2":"1","price":"8990","ca_code":"1502","goodsnm":"800G(팩)_하우스밀감","pl_no":"2365603812","deliveryinfo2":"3000","shopImageUrl":"http://image.homeplus.co.kr/UserFiles/Pressimages/94/300/112782094_0.jpg","ca_code4":"","modelno":"0","ca_codeName":"","deliveryinfo":"3000","url":"http://www.homeplus.co.kr/app.exhibition.main.PartnerMall.ghs?extends_id=enuri&service_cd=56010&nextUrl=/app.product.GoodDetail.ghs%3Fcomm%3Dusr.detail%26good_id%3D112782094%26extends_id%3Denuri%26service_cd%3D56010","imgurl":"http://image.homeplus.co.kr/UserFiles/Pressimages/94/204/112782094_0.jpg"},{"deliverytype2":"1","price":"9990","ca_code":"1502","goodsnm":"5KG(박스)_매실","pl_no":"2404817993","deliveryinfo2":"3000","shopImageUrl":"http://image.homeplus.co.kr/UserFiles/Pressimages/75/300/113328475_0.jpg","ca_code4":"","modelno":"0","ca_codeName":"","deliveryinfo":"3000","url":"http://www.homeplus.co.kr/app.exhibition.main.PartnerMall.ghs?extends_id=enuri&service_cd=56010&nextUrl=/app.product.GoodDetail.ghs%3Fcomm%3Dusr.detail%26good_id%3D113328475%26extends_id%3Denuri%26service_cd%3D56010","imgurl":"http://image.homeplus.co.kr/UserFiles/Pressimages/75/204/113328475_0.jpg"},{"deliverytype2":"1","price":"7990","ca_code":"150203","goodsnm":"400G(팩)_체리(미국)","pl_no":"2365604587","deliveryinfo2":"3000","shopImageUrl":"http://image.homeplus.co.kr/UserFiles/Pressimages/35/300/111385935_0.jpg","ca_code4":"","modelno":"0","ca_codeName":"","deliveryinfo":"3000","url":"http://www.homeplus.co.kr/app.exhibition.main.PartnerMall.ghs?extends_id=enuri&service_cd=56010&nextUrl=/app.product.GoodDetail.ghs%3Fcomm%3Dusr.detail%26good_id%3D111385935%26extends_id%3Denuri%26service_cd%3D56010","imgurl":"http://image.homeplus.co.kr/UserFiles/Pressimages/35/204/111385935_0.jpg"},{"deliverytype2":"0","price":"32900","ca_code":"15020211","goodsnm":"자연이주는건강밥상진미_20KG(포)","pl_no":"1091067433","deliveryinfo2":"0","shopImageUrl":"http://image.homeplus.co.kr/UserFiles/Pressimages/87/300/121137887_0.jpg","ca_code4":"","modelno":"10753793","ca_codeName":"","deliveryinfo":"유무료","url":"http://www.homeplus.co.kr/app.exhibition.main.PartnerMall.ghs?extends_id=enuri&service_cd=56010&nextUrl=/app.product.GoodDetail.ghs%3Fcomm%3Dusr.detail%26good_id%3D121137887%26extends_id%3Denuri%26service_cd%3D56010","imgurl":"http://image.homeplus.co.kr/UserFiles/Pressimages/87/204/121137887_0.jpg"},{"deliverytype2":"1","price":"1000","ca_code":"15020405","goodsnm":"(봉)_적상추","pl_no":"395686198","deliveryinfo2":"3000","shopImageUrl":"http://image.homeplus.co.kr/UserFiles/Pressimages/14/300/009153314_0.jpg","ca_code4":"","modelno":"2201119","ca_codeName":"","deliveryinfo":"3000","url":"http://www.homeplus.co.kr/app.exhibition.main.PartnerMall.ghs?extends_id=enuri&service_cd=56010&nextUrl=/app.product.GoodDetail.ghs%3Fcomm%3Dusr.detail%26good_id%3D009153314%26extends_id%3Denuri%26service_cd%3D56010","imgurl":"http://image.homeplus.co.kr/UserFiles/Pressimages/14/204/009153314_0.jpg"},{"deliverytype2":"1","price":"1000","ca_code":"1502","goodsnm":"(소/봉)_청양고추","pl_no":"2297139047","deliveryinfo2":"3000","shopImageUrl":"http://image.homeplus.co.kr/UserFiles/Pressimages/49/300/112786749_0.jpg","ca_code4":"","modelno":"0","ca_codeName":"","deliveryinfo":"3000","url":"http://www.homeplus.co.kr/app.exhibition.main.PartnerMall.ghs?extends_id=enuri&service_cd=56010&nextUrl=/app.product.GoodDetail.ghs%3Fcomm%3Dusr.detail%26good_id%3D112786749%26extends_id%3Denuri%26service_cd%3D56010","imgurl":"http://image.homeplus.co.kr/UserFiles/Pressimages/49/204/112786749_0.jpg"},{"deliverytype2":"1","price":"1000","ca_code":"1502","goodsnm":"봉_미니쌈추","pl_no":"395700866","deliveryinfo2":"3000","shopImageUrl":"http://image.homeplus.co.kr/UserFiles/Pressimages/32/300/113062232_0.jpg","ca_code4":"","modelno":"0","ca_codeName":"","deliveryinfo":"3000","url":"http://www.homeplus.co.kr/app.exhibition.main.PartnerMall.ghs?extends_id=enuri&service_cd=56010&nextUrl=/app.product.GoodDetail.ghs%3Fcomm%3Dusr.detail%26good_id%3D113062232%26extends_id%3Denuri%26service_cd%3D56010","imgurl":"http://image.homeplus.co.kr/UserFiles/Pressimages/32/204/113062232_0.jpg"},{"deliverytype2":"1","price":"1000","ca_code":"1502","goodsnm":"3입(봉)_깻잎","pl_no":"1028097753","deliveryinfo2":"3000","shopImageUrl":"http://image.homeplus.co.kr/UserFiles/Pressimages/92/300/122107392_0.jpg","ca_code4":"","modelno":"0","ca_codeName":"","deliveryinfo":"3000","url":"http://www.homeplus.co.kr/app.exhibition.main.PartnerMall.ghs?extends_id=enuri&service_cd=56010&nextUrl=/app.product.GoodDetail.ghs%3Fcomm%3Dusr.detail%26good_id%3D122107392%26extends_id%3Denuri%26service_cd%3D56010","imgurl":"http://image.homeplus.co.kr/UserFiles/Pressimages/92/204/122107392_0.jpg"},{"deliverytype2":"1","price":"9990","ca_code":"1504","goodsnm":"200G(봉)_아이들이 좋아하는 어린이고운멸치","pl_no":"1970815090","deliveryinfo2":"3000","shopImageUrl":"http://image.homeplus.co.kr/UserFiles/Pressimages/63/300/106503263_0.jpg","ca_code4":"","modelno":"0","ca_codeName":"","deliveryinfo":"3000","url":"http://www.homeplus.co.kr/app.exhibition.main.PartnerMall.ghs?extends_id=enuri&service_cd=56010&nextUrl=/app.product.GoodDetail.ghs%3Fcomm%3Dusr.detail%26good_id%3D106503263%26extends_id%3Denuri%26service_cd%3D56010","imgurl":"http://image.homeplus.co.kr/UserFiles/Pressimages/63/204/106503263_0.jpg"},{"deliverytype2":"1","price":"9990","ca_code":"15040409","goodsnm":"칼슘진미오징어_250G(봉)_","pl_no":"816247604","deliveryinfo2":"3000","shopImageUrl":"http://image.homeplus.co.kr/UserFiles/Pressimages/88/300/121358988_0.jpg","ca_code4":"","modelno":"10451108","ca_codeName":"","deliveryinfo":"3000","url":"http://www.homeplus.co.kr/app.exhibition.main.PartnerMall.ghs?extends_id=enuri&service_cd=56010&nextUrl=/app.product.GoodDetail.ghs%3Fcomm%3Dusr.detail%26good_id%3D121358988%26extends_id%3Denuri%26service_cd%3D56010","imgurl":"http://image.homeplus.co.kr/UserFiles/Pressimages/88/204/121358988_0.jpg"},{"deliverytype2":"1","price":"9990","ca_code":"1504","goodsnm":"두절새우(볶음용)_150g_시우드","pl_no":"2337129115","deliveryinfo2":"3000","shopImageUrl":"http://image.homeplus.co.kr/UserFiles/Goods/300/126030734_0.jpg","ca_code4":"","modelno":"0","ca_codeName":"","deliveryinfo":"3000","url":"http://www.homeplus.co.kr/app.exhibition.main.PartnerMall.ghs?extends_id=enuri&service_cd=56010&nextUrl=/app.product.GoodDetail.ghs%3Fcomm%3Dusr.detail%26good_id%3D126030734%26extends_id%3Denuri%26service_cd%3D56010","imgurl":"http://image.homeplus.co.kr/UserFiles/Goods/204/126030734_0.jpg"},{"deliverytype2":"1","price":"4990","ca_code":"15030713","goodsnm":"1000G(마리)_생닭11호","pl_no":"414458708","deliveryinfo2":"3000","shopImageUrl":"http://image.homeplus.co.kr/UserFiles/Pressimages/01/300/104690501_0.jpg","ca_code4":"","modelno":"10107515","ca_codeName":"","deliveryinfo":"3000","url":"http://www.homeplus.co.kr/app.exhibition.main.PartnerMall.ghs?extends_id=enuri&service_cd=56010&nextUrl=/app.product.GoodDetail.ghs%3Fcomm%3Dusr.detail%26good_id%3D104690501%26extends_id%3Denuri%26service_cd%3D56010","imgurl":"http://image.homeplus.co.kr/UserFiles/Pressimages/01/204/104690501_0.jpg"},{"deliverytype2":"1","price":"3990","ca_code":"15030903","goodsnm":"100G_꽃갈비살(미국산우육)","pl_no":"1942616195","deliveryinfo2":"3000","shopImageUrl":"http://image.homeplus.co.kr/UserFiles/Pressimages/16/300/115357616_0.jpg","ca_code4":"","modelno":"12255894","ca_codeName":"","deliveryinfo":"3000","url":"http://www.homeplus.co.kr/app.exhibition.main.PartnerMall.ghs?extends_id=enuri&service_cd=56010&nextUrl=/app.product.GoodDetail.ghs%3Fcomm%3Dusr.detail%26good_id%3D115357616%26extends_id%3Denuri%26service_cd%3D56010","imgurl":"http://image.homeplus.co.kr/UserFiles/Pressimages/16/204/115357616_0.jpg"},{"deliverytype2":"1","price":"1790","ca_code":"1503","goodsnm":"100G_엄지척돼지갈비/갈비살(1)","pl_no":"2357858536","deliveryinfo2":"3000","shopImageUrl":"http://image.homeplus.co.kr/UserFiles/Goods/300/126122107_0.jpg","ca_code4":"","modelno":"0","ca_codeName":"","deliveryinfo":"3000","url":"http://www.homeplus.co.kr/app.exhibition.main.PartnerMall.ghs?extends_id=enuri&service_cd=56010&nextUrl=/app.product.GoodDetail.ghs%3Fcomm%3Dusr.detail%26good_id%3D126122107%26extends_id%3Denuri%26service_cd%3D56010","imgurl":"http://image.homeplus.co.kr/UserFiles/Goods/204/126122107_0.jpg"},{"deliverytype2":"1","price":"1790","ca_code":"1503","goodsnm":"100G_엄지척돼지갈비/갈비살(2)","pl_no":"2412889221","deliveryinfo2":"3000","shopImageUrl":"http://image.homeplus.co.kr/UserFiles/Pressimages/96/300/126122096_0.jpg","ca_code4":"","modelno":"0","ca_codeName":"","deliveryinfo":"3000","url":"http://www.homeplus.co.kr/app.exhibition.main.PartnerMall.ghs?extends_id=enuri&service_cd=56010&nextUrl=/app.product.GoodDetail.ghs%3Fcomm%3Dusr.detail%26good_id%3D126122096%26extends_id%3Denuri%26service_cd%3D56010","imgurl":"http://image.homeplus.co.kr/UserFiles/Pressimages/96/204/126122096_0.jpg"},{"deliverytype2":"1","price":"8390","ca_code":"15110704","goodsnm":"하림_치킨너겟_480G","pl_no":"1765081834","deliveryinfo2":"3000","shopImageUrl":"http://image.homeplus.co.kr/UserFiles/Pressimages/55/300/123854455_0.jpg","ca_code4":"","modelno":"12136919","ca_codeName":"","deliveryinfo":"3000","url":"http://www.homeplus.co.kr/app.exhibition.main.PartnerMall.ghs?extends_id=enuri&service_cd=56010&nextUrl=/app.product.GoodDetail.ghs%3Fcomm%3Dusr.detail%26good_id%3D123854455%26extends_id%3Denuri%26service_cd%3D56010","imgurl":"http://image.homeplus.co.kr/UserFiles/Pressimages/55/204/123854455_0.jpg"},{"deliverytype2":"1","price":"9900","ca_code":"1511","goodsnm":"두마리 옛날통닭_델리","pl_no":"2413685983","deliveryinfo2":"3000","shopImageUrl":"http://image.homeplus.co.kr/UserFiles/Goods/300/126229448_0.jpg","ca_code4":"","modelno":"0","ca_codeName":"","deliveryinfo":"3000","url":"http://www.homeplus.co.kr/app.exhibition.main.PartnerMall.ghs?extends_id=enuri&service_cd=56010&nextUrl=/app.product.GoodDetail.ghs%3Fcomm%3Dusr.detail%26good_id%3D126229448%26extends_id%3Denuri%26service_cd%3D56010","imgurl":"http://image.homeplus.co.kr/UserFiles/Goods/204/126229448_0.jpg"},{"deliverytype2":"1","price":"5990","ca_code":"15110601","goodsnm":"동원_통그릴리얼비엔나_260G*2","pl_no":"2395708180","deliveryinfo2":"3000","shopImageUrl":"http://image.homeplus.co.kr/UserFiles/Goods/300/126133653_0.jpg","ca_code4":"","modelno":"0","ca_codeName":"","deliveryinfo":"3000","url":"http://www.homeplus.co.kr/app.exhibition.main.PartnerMall.ghs?extends_id=enuri&service_cd=56010&nextUrl=/app.product.GoodDetail.ghs%3Fcomm%3Dusr.detail%26good_id%3D126133653%26extends_id%3Denuri%26service_cd%3D56010","imgurl":"http://image.homeplus.co.kr/UserFiles/Goods/204/126133653_0.jpg"},{"deliverytype2":"1","price":"3990","ca_code":"15130413","goodsnm":"P)연세_우유_1L 2입기획","pl_no":"1833166716","deliveryinfo2":"3000","shopImageUrl":"http://image.homeplus.co.kr/UserFiles/Goods/300/124407402_0.jpg","ca_code4":"","modelno":"12531313","ca_codeName":"","deliveryinfo":"3000","url":"http://www.homeplus.co.kr/app.exhibition.main.PartnerMall.ghs?extends_id=enuri&service_cd=56010&nextUrl=/app.product.GoodDetail.ghs%3Fcomm%3Dusr.detail%26good_id%3D124407402%26extends_id%3Denuri%26service_cd%3D56010","imgurl":"http://image.homeplus.co.kr/UserFiles/Goods/204/124407402_0.jpg"},{"deliverytype2":"0","price":"2990","ca_code":"15110101","goodsnm":"농심_*올리브짜파게티_140G*5입","pl_no":"541894793","deliveryinfo2":"0","shopImageUrl":"http://image.homeplus.co.kr/UserFiles/Pressimages/64/300/120108964_0.jpg","ca_code4":"","modelno":"687662","ca_codeName":"","deliveryinfo":"유무료","url":"http://www.homeplus.co.kr/app.exhibition.main.PartnerMall.ghs?extends_id=enuri&service_cd=56010&nextUrl=/app.product.GoodDetail.ghs%3Fcomm%3Dusr.detail%26good_id%3D120108964%26extends_id%3Denuri%26service_cd%3D56010","imgurl":"http://image.homeplus.co.kr/UserFiles/Pressimages/64/204/120108964_0.jpg"},{"deliverytype2":"1","price":"20900","ca_code":"15050102","goodsnm":"N)동서식품_맥심모카골드믹스_230T(2760G)","pl_no":"395718822","deliveryinfo2":"3000","shopImageUrl":"http://image.homeplus.co.kr/UserFiles/Pressimages/47/300/106872747_0.jpg","ca_code4":"","modelno":"1812027","ca_codeName":"","deliveryinfo":"3000","url":"http://www.homeplus.co.kr/app.exhibition.main.PartnerMall.ghs?extends_id=enuri&service_cd=56010&nextUrl=/app.product.GoodDetail.ghs%3Fcomm%3Dusr.detail%26good_id%3D106872747%26extends_id%3Denuri%26service_cd%3D56010","imgurl":"http://image.homeplus.co.kr/UserFiles/Pressimages/47/204/106872747_0.jpg"},{"deliverytype2":"1","price":"5460","ca_code":"15130102","goodsnm":"CP_6_코카콜라_휘오제주_2L*6","pl_no":"741856547","deliveryinfo2":"3000","shopImageUrl":"http://image.homeplus.co.kr/UserFiles/Pressimages/80/300/114735380_0.jpg","ca_code4":"","modelno":"2185558","ca_codeName":"","deliveryinfo":"3000","url":"http://www.homeplus.co.kr/app.exhibition.main.PartnerMall.ghs?extends_id=enuri&service_cd=56010&nextUrl=/app.product.GoodDetail.ghs%3Fcomm%3Dusr.detail%26good_id%3D114735380%26extends_id%3Denuri%26service_cd%3D56010","imgurl":"http://image.homeplus.co.kr/UserFiles/Pressimages/80/204/114735380_0.jpg"},{"deliverytype2":"1","price":"1990","ca_code":"15130213","goodsnm":"롯데칠성_칠성사이다_190ML*6","pl_no":"791167841","deliveryinfo2":"3000","shopImageUrl":"http://image.homeplus.co.kr/UserFiles/Goods/300/121165628_0.jpg","ca_code4":"","modelno":"9073430","ca_codeName":"","deliveryinfo":"3000","url":"http://www.homeplus.co.kr/app.exhibition.main.PartnerMall.ghs?extends_id=enuri&service_cd=56010&nextUrl=/app.product.GoodDetail.ghs%3Fcomm%3Dusr.detail%26good_id%3D121165628%26extends_id%3Denuri%26service_cd%3D56010","imgurl":"http://image.homeplus.co.kr/UserFiles/Pressimages/28/204/121165628_0.jpg"},{"deliverytype2":"1","price":"7590","ca_code":"15110301","goodsnm":"CJ_둥근햇반실속8입_210G*8","pl_no":"1091068442","deliveryinfo2":"3000","shopImageUrl":"http://image.homeplus.co.kr/UserFiles/Pressimages/89/300/122303689_0.jpg","ca_code4":"","modelno":"10352533","ca_codeName":"","deliveryinfo":"3000","url":"http://www.homeplus.co.kr/app.exhibition.main.PartnerMall.ghs?extends_id=enuri&service_cd=56010&nextUrl=/app.product.GoodDetail.ghs%3Fcomm%3Dusr.detail%26good_id%3D122303689%26extends_id%3Denuri%26service_cd%3D56010","imgurl":"http://image.homeplus.co.kr/UserFiles/Pressimages/89/204/122303689_0.jpg"},{"deliverytype2":"1","price":"16800","ca_code":"16140103","goodsnm":"모나리자_나무이야기3겹데코화장지_27M*30R","pl_no":"722078586","deliveryinfo2":"3000","shopImageUrl":"http://image.homeplus.co.kr/UserFiles/Goods/300/120922558_0.jpg","ca_code4":"","modelno":"11621144","ca_codeName":"","deliveryinfo":"3000","url":"http://www.homeplus.co.kr/app.exhibition.main.PartnerMall.ghs?extends_id=enuri&service_cd=56010&nextUrl=/app.product.GoodDetail.ghs%3Fcomm%3Dusr.detail%26good_id%3D120922558%26extends_id%3Denuri%26service_cd%3D56010","imgurl":"http://image.homeplus.co.kr/UserFiles/Pressimages/58/204/120922558_0.jpg"},{"deliverytype2":"1","price":"9900","ca_code":"1629","goodsnm":"LG생활건강_MR.홈스타습기좀부탁해_8P","pl_no":"2413685455","deliveryinfo2":"3000","shopImageUrl":"http://image.homeplus.co.kr/UserFiles/Pressimages/84/300/126229984_0.jpg","ca_code4":"","modelno":"0","ca_codeName":"","deliveryinfo":"3000","url":"http://www.homeplus.co.kr/app.exhibition.main.PartnerMall.ghs?extends_id=enuri&service_cd=56010&nextUrl=/app.product.GoodDetail.ghs%3Fcomm%3Dusr.detail%26good_id%3D126229984%26extends_id%3Denuri%26service_cd%3D56010","imgurl":"http://image.homeplus.co.kr/UserFiles/Pressimages/84/204/126229984_0.jpg"},{"deliverytype2":"1","price":"2990","ca_code":"1625","goodsnm":"슈가버블_천연성분베이킹소다리필_2KG","pl_no":"2228149937","deliveryinfo2":"3000","shopImageUrl":"http://image.homeplus.co.kr/UserFiles/Pressimages/20/300/125696120_0.jpg","ca_code4":"","modelno":"0","ca_codeName":"","deliveryinfo":"3000","url":"http://www.homeplus.co.kr/app.exhibition.main.PartnerMall.ghs?extends_id=enuri&service_cd=56010&nextUrl=/app.product.GoodDetail.ghs%3Fcomm%3Dusr.detail%26good_id%3D125696120%26extends_id%3Denuri%26service_cd%3D56010","imgurl":"http://image.homeplus.co.kr/UserFiles/Pressimages/20/204/125696120_0.jpg"},{"deliverytype2":"1","price":"2990","ca_code":"1625","goodsnm":"슈가버블_천연성분과탄산소다리필_1KG","pl_no":"2242466475","deliveryinfo2":"3000","shopImageUrl":"http://image.homeplus.co.kr/UserFiles/Pressimages/37/300/125696137_0.jpg","ca_code4":"","modelno":"0","ca_codeName":"","deliveryinfo":"3000","url":"http://www.homeplus.co.kr/app.exhibition.main.PartnerMall.ghs?extends_id=enuri&service_cd=56010&nextUrl=/app.product.GoodDetail.ghs%3Fcomm%3Dusr.detail%26good_id%3D125696137%26extends_id%3Denuri%26service_cd%3D56010","imgurl":"http://image.homeplus.co.kr/UserFiles/Pressimages/37/204/125696137_0.jpg"},{"deliverytype2":"1","price":"2990","ca_code":"1625","goodsnm":"슈가버블_천연성분구연산리필_1KG","pl_no":"2242466489","deliveryinfo2":"3000","shopImageUrl":"http://image.homeplus.co.kr/UserFiles/Pressimages/55/300/125696155_0.jpg","ca_code4":"","modelno":"0","ca_codeName":"","deliveryinfo":"3000","url":"http://www.homeplus.co.kr/app.exhibition.main.PartnerMall.ghs?extends_id=enuri&service_cd=56010&nextUrl=/app.product.GoodDetail.ghs%3Fcomm%3Dusr.detail%26good_id%3D125696155%26extends_id%3Denuri%26service_cd%3D56010","imgurl":"http://image.homeplus.co.kr/UserFiles/Pressimages/55/204/125696155_0.jpg"},{"deliverytype2":"1","price":"7900","ca_code":"16210109","goodsnm":"다성_글라스락캐니스터2L_2P","pl_no":"2213901348","deliveryinfo2":"3000","shopImageUrl":"http://image.homeplus.co.kr/UserFiles/Pressimages/28/300/125549128_0.jpg","ca_code4":"","modelno":"7723909","ca_codeName":"","deliveryinfo":"3000","url":"http://www.homeplus.co.kr/app.exhibition.main.PartnerMall.ghs?extends_id=enuri&service_cd=56010&nextUrl=/app.product.GoodDetail.ghs%3Fcomm%3Dusr.detail%26good_id%3D125549128%26extends_id%3Denuri%26service_cd%3D56010","imgurl":"http://image.homeplus.co.kr/UserFiles/Pressimages/28/204/125549128_0.jpg"},{"deliverytype2":"1","price":"9900","ca_code":"1208","goodsnm":"The Home_쿨링프레쉬엠보이불_145*200","pl_no":"2365605306","deliveryinfo2":"3000","shopImageUrl":"http://image.homeplus.co.kr/UserFiles/Pressimages/97/300/126135697_0.jpg","ca_code4":"","modelno":"0","ca_codeName":"","deliveryinfo":"3000","url":"http://www.homeplus.co.kr/app.exhibition.main.PartnerMall.ghs?extends_id=enuri&service_cd=56010&nextUrl=/app.product.GoodDetail.ghs%3Fcomm%3Dusr.detail%26good_id%3D126135697%26extends_id%3Denuri%26service_cd%3D56010","imgurl":"http://image.homeplus.co.kr/UserFiles/Pressimages/97/204/126135697_0.jpg"},{"deliverytype2":"1","price":"8900","ca_code":"1626","goodsnm":"키친아트_다이아몬드코팅주물프라이팬_28cm","pl_no":"2413685488","deliveryinfo2":"3000","shopImageUrl":"http://image.homeplus.co.kr/UserFiles/Pressimages/90/300/126186590_0.jpg","ca_code4":"","modelno":"0","ca_codeName":"","deliveryinfo":"3000","url":"http://www.homeplus.co.kr/app.exhibition.main.PartnerMall.ghs?extends_id=enuri&service_cd=56010&nextUrl=/app.product.GoodDetail.ghs%3Fcomm%3Dusr.detail%26good_id%3D126186590%26extends_id%3Denuri%26service_cd%3D56010","imgurl":"http://image.homeplus.co.kr/UserFiles/Pressimages/90/204/126186590_0.jpg"}],"totalCnt":36}